Metadata-Version: 2.1
Name: unicodeit
Version: 0.7.5
Summary: Converts LaTeX tags to unicode
Home-page: https://github.com/svenkreiss/unicodeit
Author: Sven Kreiss
Author-email: research@svenkreiss.com
License: MIT
Platform: UNKNOWN
Provides-Extra: dev
